README.txt
bayes_cluster.py
setup.py
bayes_cluster.egg-info/PKG-INFO
bayes_cluster.egg-info/SOURCES.txt
bayes_cluster.egg-info/dependency_links.txt
bayes_cluster.egg-info/requires.txt
bayes_cluster.egg-info/top_level.txt